guzzy/__init__.py
guzzy/__main__.py
guzzy/commands/diff.sh
guzzy/commands/file-history.sh
guzzy/commands/files.sh
guzzy/commands/log.sh
guzzy/commands/tags.sh
guzzy-0.1.7.dist-info/entry_points.txt
guzzy-0.1.7.dist-info/LICENSE
guzzy-0.1.7.dist-info/WHEEL
guzzy-0.1.7.dist-info/METADATA
guzzy-0.1.7.dist-info/RECORD
